MANIFEST.in
README_pypi.md
setup.cfg
setup.py
ipymessenger/IpmsgHostinfo.py
ipymessenger/IpmsgMessage.py
ipymessenger/IpmsgServer.py
ipymessenger/__init__.py
ipymessenger/common.py
ipymessenger/consts.py
ipymessenger.egg-info/PKG-INFO
ipymessenger.egg-info/SOURCES.txt
ipymessenger.egg-info/dependency_links.txt
ipymessenger.egg-info/top_level.txt