Metadata-Version: 1.1
Name: ipymessenger
Version: 0.0.5
Summary: ip messenger library fro python
Home-page: https://github.com/denzow/ipymessenger
Author: denzow
Author-email: denzow@example.com
License: MIT
Keywords: ipmessenger
Platform: UNKNOWN
Classifier: Development Status :: 1 - Planning
Classifier: License :: OSI Approved :: MIT License
Classifier: Programming Language :: Python
Classifier: Topic :: Software Development
